wikiscraperx/__init__.py
wikiscraperx/__main__.py
wikiscraperx/cli.py
wikiscraperx/mainCli.py
wikiscraperx/tableParser.py
wikiscraperx-1.0.6.data/scripts/wikiscraperx
wikiscraperx-1.0.6.dist-info/licenses/LICENSE
wikiscraperx-1.0.6.dist-info/METADATA
wikiscraperx-1.0.6.dist-info/WHEEL
wikiscraperx-1.0.6.dist-info/entry_points.txt
wikiscraperx-1.0.6.dist-info/top_level.txt
wikiscraperx-1.0.6.dist-info/RECORD
