Metadata-Version: 2.4
Name: wikiscraperx
Version: 1.0.6
Summary: Scrape Wikipedia tables into CSVs or JSON
Home-page: https://github.com/Joseph-Press/wikiscraperx
Download-URL: https://github.com/Joseph-Press/WikiScraperX/archive/refs/tags/1.0.4.1.tar.gz
Author: Joseph Press
Author-email: Joseph Press <joepress101@gmail.com>
License: MIT
Project-URL: Homepage, https://github.com/Joseph-Press/wikiscraperx
Classifier: Development Status :: 4 - Beta
Classifier: Programming Language :: Python :: 3
Classifier: License :: OSI Approved :: MIT License
Classifier: Operating System :: OS Independent
Requires-Python: >=3.7
License-File: LICENSE
Requires-Dist: requests
Requires-Dist: beautifulsoup4
Requires-Dist: lxml
Dynamic: author
Dynamic: download-url
Dynamic: home-page
Dynamic: license-file
